curare/__init__.py
curare/curare.py
curare/curare_wizard.py
curare/metadata.py
curare/lib/__init__.py
curare/lib/generate_report.py
curare/lib/parse_versions.py
curare/report/report.html
curare/report/css/buefy.min.css
curare/report/css/bulma.min.css
curare/report/css/report.css
curare/report/img/buefy-logo.png
curare/report/img/bulma.png
curare/report/img/chartjs.svg
curare/report/img/vuejs.png
curare/report/js/Chart.min.js
curare/report/js/buefy.min.js
curare/report/js/fontawesome.all.min.js
curare/report/js/footer.js
curare/report/js/navigation_bar.js
curare/report/js/overview.js
curare/report/js/vue-chartjs.min.js
curare/report/js/vue.min.js
curare/report/modules/about.html
curare/snakefiles/analysis/count_table/count_table.yaml
curare/snakefiles/analysis/count_table/count_table_pe
curare/snakefiles/analysis/count_table/count_table_se
curare/snakefiles/analysis/count_table/lib/conda_env.yaml
curare/snakefiles/analysis/count_table/lib/generate_report_data.py
curare/snakefiles/analysis/count_table/lib/report/count_table.html
curare/snakefiles/analysis/count_table/lib/report/count_table.js
curare/snakefiles/analysis/dge_analysis/dge_analysis.yaml
curare/snakefiles/analysis/dge_analysis/dge_analysis_pe
curare/snakefiles/analysis/dge_analysis/dge_analysis_se
curare/snakefiles/analysis/dge_analysis/lib/conda_env.yaml
curare/snakefiles/analysis/dge_analysis/lib/deseq2_analysis_create_comparison_files_and_summary.R
curare/snakefiles/analysis/dge_analysis/lib/deseq2_analysis_normalize_counts.R
curare/snakefiles/analysis/dge_analysis/lib/deseq2_summary_tsv_to_xlsx.py
curare/snakefiles/analysis/dge_analysis/lib/generate_report_data.py
curare/snakefiles/analysis/dge_analysis/lib/gff_to_rseqc_bed.py
curare/snakefiles/analysis/dge_analysis/lib/visualize_assignments.py
curare/snakefiles/analysis/dge_analysis/lib/report/dge_analysis.css
curare/snakefiles/analysis/dge_analysis/lib/report/dge_analysis.html
curare/snakefiles/analysis/dge_analysis/lib/report/dge_analysis.js
Curare-0.6.0.dist-info/LICENSE
Curare-0.6.0.dist-info/METADATA
Curare-0.6.0.dist-info/WHEEL
Curare-0.6.0.dist-info/entry_points.txt
Curare-0.6.0.dist-info/top_level.txt
Curare-0.6.0.dist-info/RECORD
