Metadata-Version: 2.1
Name: Curare
Version: 0.6.0
Summary: Curare: A Customizable and Reproducible Analysis Pipeline for RNA-Seq Experiments
Home-page: https://github.com/pblumenkamp/Curare
Author: Patrick Blumenkamp
Author-email: patrick.blumenkamp@computational.bio.uni-giessen.de
License: GPLv3
Project-URL: Bug Reports, https://https://github.com/pblumenkamp/Curare/issues
Project-URL: Source, https://github.com/pblumenkamp/Curare
Keywords: bioinformatics,rna-seq,differential-gene-expression,transcriptomics
Platform: UNKNOWN
Classifier: Operating System :: POSIX :: Linux
Classifier: Programming Language :: Python :: 3 :: Only
Classifier: Programming Language :: Python :: 3.10
Classifier: Development Status :: 5 - Production/Stable
Classifier: License :: OSI Approved :: GNU General Public License v3 (GPLv3)
Classifier: Topic :: Scientific/Engineering :: Bio-Informatics
Classifier: Environment :: Console
Classifier: Intended Audience :: Science/Research
Classifier: Natural Language :: English
Requires-Python: >=3.10
Requires-Dist: PyYAML ==6.0.1
Requires-Dist: docopt ==0.6.2
Requires-Dist: snakemake ==7.32.3
Requires-Dist: progressbar2 ==4.3.2
Requires-Dist: biopython ==1.83
